[
  {
    "name": "UEFA EURO 2020",
    "start_date": "2021-06-11 21:00:00 Europe/Brussels",
    "end_date": "2021-07-11 22:45:00 Europe/Brussels",
    "logo_url": "https://img.uefa.com/imgml/uefacom/euro2020/logo.png",
    "groups": [
      {
        "name": "A",
        "fixtures": [
          {
            "home": "TUR",
            "away": "ITA",
            "kickoff": "2021-06-11 21:00:00 Europe/Brussels"
          },
          {
            "home": "WAL",
            "away": "CHE",
            "kickoff": "2021-06-12 15:00:00 Europe/Brussels"
          },
          {
            "home": "TUR",
            "away": "WAL",
            "kickoff": "2021-06-16 18:00:00 Europe/Brussels"
          },
          {
            "home": "ITA",
            "away": "CHE",
            "kickoff": "2021-06-16 21:00:00 Europe/Brussels"
          },
          {
            "home": "ITA",
            "away": "WAL",
            "kickoff": "2021-06-20 18:00:00 Europe/Brussels"
          },
          {
            "home": "CHE",
            "away": "TUR",
            "kickoff": "2021-06-20 18:00:00 Europe/Brussels"
          }
        ]
      },
      {
        "name": "B",
        "fixtures": [
          {
            "home": "DNK",
            "away": "FIN",
            "kickoff": "2021-06-12 18:00:00 Europe/Brussels"
          },
          {
            "home": "BEL",
            "away": "RUS",
            "kickoff": "2021-06-12 21:00:00 Europe/Brussels"
          },
          {
            "home": "FIN",
            "away": "RUS",
            "kickoff": "2021-06-16 15:00:00 Europe/Brussels"
          },
          {
            "home": "DNK",
            "away": "BEL",
            "kickoff": "2021-06-17 18:00:00 Europe/Brussels"
          },
          {
            "home": "RUS",
            "away": "DNK",
            "kickoff": "2021-06-21 21:00:00 Europe/Brussels"
          },
          {
            "home": "FIN",
            "away": "BEL",
            "kickoff": "2021-06-21 21:00:00 Europe/Brussels"
          }
        ]
      },
      {
        "name": "C",
        "fixtures": [
          {
            "home": "AUT",
            "away": "MKD",
            "kickoff": "2021-06-13 18:00:00 Europe/Brussels"
          },
          {
            "home": "NLD",
            "away": "UKR",
            "kickoff": "2021-06-13 21:00:00 Europe/Brussels"
          },
          {
            "home": "UKR",
            "away": "MKD",
            "kickoff": "2021-06-17 15:00:00 Europe/Brussels"
          },
          {
            "home": "NLD",
            "away": "AUT",
            "kickoff": "2021-06-17 21:00:00 Europe/Brussels"
          },
          {
            "home": "UKR",
            "away": "AUT",
            "kickoff": "2021-06-21 18:00:00 Europe/Brussels"
          },
          {
            "home": "MKD",
            "away": "NLD",
            "kickoff": "2021-06-21 18:00:00 Europe/Brussels"
          }
        ]
      },
      {
        "name": "D",
        "fixtures": [
          {
            "home": "ENG",
            "away": "HRV",
            "kickoff": "2021-06-13 15:00:00 Europe/Brussels"
          },
          {
            "home": "SCO",
            "away": "CZE",
            "kickoff": "2021-06-14 15:00:00 Europe/Brussels"
          },
          {
            "home": "HRV",
            "away": "CZE",
            "kickoff": "2021-06-18 18:00:00 Europe/Brussels"
          },
          {
            "home": "ENG",
            "away": "SCO",
            "kickoff": "2021-06-18 21:00:00 Europe/Brussels"
          },
          {
            "home": "HRV",
            "away": "SCO",
            "kickoff": "2021-06-22 21:00:00 Europe/Brussels"
          },
          {
            "home": "CZE",
            "away": "ENG",
            "kickoff": "2021-06-22 21:00:00 Europe/Brussels"
          }
        ]
      },
      {
        "name": "E",
        "fixtures": [
          {
            "home": "POL",
            "away": "SVK",
            "kickoff": "2021-06-14 18:00:00 Europe/Brussels"
          },
          {
            "home": "ESP",
            "away": "SWE",
            "kickoff": "2021-06-14 21:00:00 Europe/Brussels"
          },
          {
            "home": "SWE",
            "away": "SVK",
            "kickoff": "2021-06-18 15:00:00 Europe/Brussels"
          },
          {
            "home": "ESP",
            "away": "POL",
            "kickoff": "2021-06-19 21:00:00 Europe/Brussels"
          },
          {
            "home": "SWE",
            "away": "POL",
            "kickoff": "2021-06-23 18:00:00 Europe/Brussels"
          },
          {
            "home": "SVK",
            "away": "ESP",
            "kickoff": "2021-06-23 18:00:00 Europe/Brussels"
          }
        ]
      },
      {
        "name": "F",
        "fixtures": [
          {
            "home": "HUN",
            "away": "PRT",
            "kickoff": "2021-06-15 18:00:00 Europe/Brussels"
          },
          {
            "home": "FRA",
            "away": "DEU",
            "kickoff": "2021-06-15 21:00:00 Europe/Brussels"
          },
          {
            "home": "HUN",
            "away": "FRA",
            "kickoff": "2021-06-19 15:00:00 Europe/Brussels"
          },
          {
            "home": "PRT",
            "away": "DEU",
            "kickoff": "2021-06-19 18:00:00 Europe/Brussels"
          },
          {
            "home": "PRT",
            "away": "FRA",
            "kickoff": "2021-06-23 21:00:00 Europe/Brussels"
          },
          {
            "home": "DEU",
            "away": "HUN",
            "kickoff": "2021-06-23 21:00:00 Europe/Brussels"
          }
        ]
      }
    ],
    "bracket": [
      {
        "name": "Round of 16",
        "fixtures": [
          { "home": "2A", "away": "2B", "kickoff": "" },
          { "home": "1A", "away": "2C", "kickoff": "" },
          { "home": "1C", "away": "3DEF", "kickoff": "" },
          { "home": "1B", "away": "3ADEF", "kickoff": "" },
          { "home": "2A", "away": "2B", "kickoff": "" },
          { "home": "1A", "away": "2C", "kickoff": "" },
          { "home": "2A", "away": "2B", "kickoff": "" },
          { "home": "1A", "away": "2C", "kickoff": "" }
        ]
      }
    ]
  }
]
